README.md
setup.py
commons/Table.py
commons/__init__.py
commons/crypto.py
commons/formatting.py
commons/net.py
commons/shell.py
commons/terminal.py
commons/utils.py
mcommons.egg-info/PKG-INFO
mcommons.egg-info/SOURCES.txt
mcommons.egg-info/dependency_links.txt
mcommons.egg-info/pbr.json
mcommons.egg-info/requires.txt
mcommons.egg-info/top_level.txt